embasi/__init__.py
embasi/asi_default_callbacks.py
embasi/atoms_embedding_asi.py
embasi/basis_info.py
embasi/chemsh_interface.py
embasi/embedding.py
embasi/parallel_utils.py
embasi/roothan_hall_eigensolver.py
embasi/roothan_hall_eigensolver_scalapack.py
embasi/write_aims.py
embasi-0.4.3.dist-info/licenses/LICENSE
embasi-0.4.3.dist-info/METADATA
embasi-0.4.3.dist-info/WHEEL
embasi-0.4.3.dist-info/top_level.txt
embasi-0.4.3.dist-info/RECORD
