Metadata-Version: 2.4
Name: embasi
Version: 0.4.3
Summary: A generalised workflow for QM/QM Embedding
Author-email: Gabriel Bramley <BramleyG@cardiff.ac.uk>
License: MIT License
Project-URL: Homepage, https://github.com/logsdail/EmbASI
Project-URL: Issues, https://github.com/logsdail/EmbASI/issues
Classifier: Programming Language :: Python :: 3
Classifier: License :: OSI Approved :: MIT License
Classifier: Operating System :: OS Independent
Requires-Python: >=3.9
License-File: LICENSE
Requires-Dist: ase==3.24.0
Requires-Dist: asi4py>=1.4.5
Requires-Dist: scalapack4py>=0.2.0
Dynamic: license-file
